clustexts/__init__.py
clustexts/clustexts.py
clustexts-0.0.1.dist-info/LICENSE
clustexts-0.0.1.dist-info/METADATA
clustexts-0.0.1.dist-info/WHEEL
clustexts-0.0.1.dist-info/top_level.txt
clustexts-0.0.1.dist-info/RECORD
