Metadata-Version: 2.2
Name: clustexts
Version: 0.0.1
Author-email: Jordi Carrera Ventura <jordi.carrera.ventura@gmail.com>
Project-URL: GitHub repository, https://github.com/JordiCarreraVentura/clustexts
Project-URL: Similar project (independent), https://github.com/anshulp2912/automeans
Classifier: Programming Language :: Python :: 3
Classifier: Operating System :: OS Independent
Requires-Python: >=3.11
License-File: LICENSE
Requires-Dist: Unidecode==1.3.8
Requires-Dist: build
Requires-Dist: matplotlib==3.10.1
Requires-Dist: numpy==2.2.3
Requires-Dist: pandas==2.2.3
Requires-Dist: pytest==8.3.5
Requires-Dist: scikit-learn==1.6.1
Requires-Dist: scipy==1.15.2
Requires-Dist: seaborn==0.13.2
Requires-Dist: tqdm==4.67.1
Requires-Dist: twine
